LICENSE
MANIFEST.in
README.md
setup.cfg
setup.py
stdeb.cfg
./web2ldap/__about__.py
./web2ldap/__init__.py
./web2ldap/__main__.py
./web2ldap/checkinst.py
./web2ldap/ldapsession.py
./web2ldap/log.py
./web2ldap/msbase.py
./web2ldap/utctime.py
./web2ldap/app/__init__.py
./web2ldap/app/add.py
./web2ldap/app/addmodifyform.py
./web2ldap/app/bulkmod.py
./web2ldap/app/cnf.py
./web2ldap/app/connect.py
./web2ldap/app/conninfo.py
./web2ldap/app/dds.py
./web2ldap/app/delete.py
./web2ldap/app/dit.py
./web2ldap/app/entry.py
./web2ldap/app/form.py
./web2ldap/app/groupadm.py
./web2ldap/app/gui.py
./web2ldap/app/handler.py
./web2ldap/app/locate.py
./web2ldap/app/login.py
./web2ldap/app/metrics.py
./web2ldap/app/modify.py
./web2ldap/app/monitor.py
./web2ldap/app/params.py
./web2ldap/app/passwd.py
./web2ldap/app/read.py
./web2ldap/app/referral.py
./web2ldap/app/rename.py
./web2ldap/app/search.py
./web2ldap/app/searchform.py
./web2ldap/app/session.py
./web2ldap/app/srvrr.py
./web2ldap/app/stats.py
./web2ldap/app/tmpl.py
./web2ldap/app/urlredirect.py
./web2ldap/app/plugins/__init__.py
./web2ldap/app/plugins/acp133.py
./web2ldap/app/plugins/activedirectory.py
./web2ldap/app/plugins/aedir.py
./web2ldap/app/plugins/apple.py
./web2ldap/app/plugins/asn1objects.py
./web2ldap/app/plugins/dds.py
./web2ldap/app/plugins/debian.py
./web2ldap/app/plugins/demail.py
./web2ldap/app/plugins/dhcp.py
./web2ldap/app/plugins/dnsdomain.py
./web2ldap/app/plugins/dnszone.py
./web2ldap/app/plugins/dyngroup.py
./web2ldap/app/plugins/edirectory.py
./web2ldap/app/plugins/eduperson.py
./web2ldap/app/plugins/entrust.py
./web2ldap/app/plugins/exchange.py
./web2ldap/app/plugins/freeipa.py
./web2ldap/app/plugins/freeradius.py
./web2ldap/app/plugins/groups.py
./web2ldap/app/plugins/h350.py
./web2ldap/app/plugins/ibmds.py
./web2ldap/app/plugins/inetorgperson.py
./web2ldap/app/plugins/krb5.py
./web2ldap/app/plugins/ldapns.py
./web2ldap/app/plugins/lotusdomino.py
./web2ldap/app/plugins/msperson.py
web2ldap.egg-info/PKG-INFO
web2ldap.egg-info/SOURCES.txt
web2ldap.egg-info/dependency_links.txt
web2ldap.egg-info/entry_points.txt
web2ldap.egg-info/not-zip-safe
web2ldap.egg-info/requires.txt
web2ldap.egg-info/top_level.txt